{
    "etag": "bhH1nQft89kPlx4CEzL4me5jQ2Q",
    "items": [
        {
            "etag": "b1vcnUMDZb6yq9KPLeFLc7kD1h0",
            "id": {
                "kind": "youtube#video",
                "videoId": "svP8F9BYjhI"
            },
            "kind": "youtube#searchResult",
            "snippet": {
                "channelId": "UCqBAbqbx4q7G5upsptccdPA",
                "channelTitle": "Pepe El Mago",
                "description": "Listo para descubrir La 1\u00aa Temporada: Videojuegos Felices con Historias de Fondo Espeluznantes? Acomp\u00e1\u00f1ame en este top!",
                "liveBroadcastContent": "none",
                "publishTime": "2022-07-29T20:30:08Z",
                "publishedAt": "2022-07-29T20:30:08Z",
                "thumbnails": {
                    "default": {
                        "height": 90,
                        "url": "https://i.ytimg.com/vi/svP8F9BYjhI/default.jpg",
                        "width": 120
                    },
                    "high": {
                        "height": 360,
                        "url": "https://i.ytimg.com/vi/svP8F9BYjhI/hqdefault.jpg",
                        "width": 480
                    },
                    "medium": {
                        "height": 180,
                        "url": "https://i.ytimg.com/vi/svP8F9BYjhI/mqdefault.jpg",
                        "width": 320
                    }
                },
                "title": "1\u00aa Temporada: Videojuegos Felices con Historias de Fondo Espeluznantes"
            }
        },
        {
            "etag": "WQQwBgxbu4XTzcDU8kUUj63QGCQ",
            "id": {
                "kind": "youtube#video",
                "videoId": "NHhJufIeFLo"
            },
            "kind": "youtube#searchResult",
            "snippet": {
                "channelId": "UCXoPy1Q1G39fCemCMAmiorQ",
                "channelTitle": "Zico Tops",
                "description": "Acompa\u00f1ame a conocer logros \u00e9picos en tus juegos favoritos, no te los puedes perder! Suscribete a Zico Tops para mas listas de ...",
                "liveBroadcastContent": "none",
                "publishTime": "2022-12-06T22:45:05Z",
                "publishedAt": "2022-12-06T22:45:05Z",
                "thumbnails": {
                    "default": {
                        "height": 90,
                        "url": "https://i.ytimg.com/vi/NHhJufIeFLo/default.jpg",
                        "width": 120
                    },
                    "high": {
                        "height": 360,
                        "url": "https://i.ytimg.com/vi/NHhJufIeFLo/hqdefault.jpg",
                        "width": 480
                    },
                    "medium": {
                        "height": 180,
                        "url": "https://i.ytimg.com/vi/NHhJufIeFLo/mqdefault.jpg",
                        "width": 320
                    }
                },
                "title": "1\u00aa Temporada &quot;Haza\u00f1as de Videojuegos tan Incre\u00edbles que Parecen Imposibles&quot;"
            }
        },
        {
            "etag": "7lfQ2HnpT6WMRkjzumSsOquRTU8",
            "id": {
                "kind": "youtube#video",
                "videoId": "mkAAt19h4DI"
            },
            "kind": "youtube#searchResult",
            "snippet": {
                "channelId": "UCQnSQLzMbkSN5j0rtYyPnmQ",
                "channelTitle": "Bea Dibujuegos",
                "description": "Suscr\u00edbete Gratis a Nuestro Canal para enterarte de Nuevos Nuevos! Si te gusta este tipo de juegos de dibujos animados para ...",
                "liveBroadcastContent": "none",
                "publishTime": "2017-07-11T13:18:37Z",
                "publishedAt": "2017-07-11T13:18:37Z",
                "thumbnails": {
                    "default": {
                        "height": 90,
                        "url": "https://i.ytimg.com/vi/mkAAt19h4DI/default.jpg",
                        "width": 120
                    },
                    "high": {
                        "height": 360,
                        "url": "https://i.ytimg.com/vi/mkAAt19h4DI/hqdefault.jpg",
                        "width": 480
                    },
                    "medium": {
                        "height": 180,
                        "url": "https://i.ytimg.com/vi/mkAAt19h4DI/mqdefault.jpg",
                        "width": 320
                    }
                },
                "title": "1 Hora de SUBWAY SURFERS - Jugando Subway Surfers entre Trenes - Surfistas del Subterr\u00e1neo"
            }
        },
        {
            "etag": "CmUnauwvy6xHAEmJjgbtw0MH0ww",
            "id": {
                "kind": "youtube#video",
                "videoId": "k3F5ZzXoDdM"
            },
            "kind": "youtube#searchResult",
            "snippet": {
                "channelId": "UClNSdNAqetoA97IG9zvscow",
                "channelTitle": "La Caverna del Gamer",
                "description": "Juegos y Tarjetas Prepago M\u00e1s Baratas: https://www.eneba.com/es/?af_id=caverna Descarga la APP de Eneba y obt\u00e9n ...",
                "liveBroadcastContent": "none",
                "publishTime": "2023-10-05T16:00:37Z",
                "publishedAt": "2023-10-05T16:00:37Z",
                "thumbnails": {
                    "default": {
                        "height": 90,
                        "url": "https://i.ytimg.com/vi/k3F5ZzXoDdM/default.jpg",
                        "width": 120
                    },
                    "high": {
                        "height": 360,
                        "url": "https://i.ytimg.com/vi/k3F5ZzXoDdM/hqdefault.jpg",
                        "width": 480
                    },
                    "medium": {
                        "height": 180,
                        "url": "https://i.ytimg.com/vi/k3F5ZzXoDdM/mqdefault.jpg",
                        "width": 320
                    }
                },
                "title": "10 REMAKES y REMASTERS de VIDEOJUEGOS que NOS ESPERAN en 2024"
            }
        },
        {
            "etag": "E0GCe2gja9_eNkeoRj0_Z0RwITU",
            "id": {
                "kind": "youtube#video",
                "videoId": "ou9tTWqFZ_M"
            },
            "kind": "youtube#searchResult",
            "snippet": {
                "channelId": "UC4BtoPpW5BkTO4J21-KAgsg",
                "channelTitle": "Soy Thalas",
                "description": "S\u00edgueme en INSTAGRAM: https://www.instagram.com/soythalas/",
                "liveBroadcastContent": "none",
                "publishTime": "2022-11-01T22:54:18Z",
                "publishedAt": "2022-11-01T22:54:18Z",
                "thumbnails": {
                    "default": {
                        "height": 90,
                        "url": "https://i.ytimg.com/vi/ou9tTWqFZ_M/default.jpg",
                        "width": 120
                    },
                    "high": {
                        "height": 360,
                        "url": "https://i.ytimg.com/vi/ou9tTWqFZ_M/hqdefault.jpg",
                        "width": 480
                    },
                    "medium": {
                        "height": 180,
                        "url": "https://i.ytimg.com/vi/ou9tTWqFZ_M/mqdefault.jpg",
                        "width": 320
                    }
                },
                "title": "10 VIDEOJUEGOS que son OBRAS MAESTRAS \ud83d\ude0d\ud83e\udd2f #videojuegos #shorts"
            }
        },
        {
            "etag": "d3SB48gAmF4Wy7M23ePpybJ_j_c",
            "id": {
                "kind": "youtube#video",
                "videoId": "XCwAIabfh5M"
            },
            "kind": "youtube#searchResult",
            "snippet": {
                "channelId": "UClNSdNAqetoA97IG9zvscow",
                "channelTitle": "La Caverna del Gamer",
                "description": "Juegos y Tarjetas Prepago M\u00e1s Baratas: https://www.eneba.com/es/?af_id=caverna Descarga la APP de Eneba y obt\u00e9n ...",
                "liveBroadcastContent": "none",
                "publishTime": "2023-09-12T16:00:18Z",
                "publishedAt": "2023-09-12T16:00:18Z",
                "thumbnails": {
                    "default": {
                        "height": 90,
                        "url": "https://i.ytimg.com/vi/XCwAIabfh5M/default.jpg",
                        "width": 120
                    },
                    "high": {
                        "height": 360,
                        "url": "https://i.ytimg.com/vi/XCwAIabfh5M/hqdefault.jpg",
                        "width": 480
                    },
                    "medium": {
                        "height": 180,
                        "url": "https://i.ytimg.com/vi/XCwAIabfh5M/mqdefault.jpg",
                        "width": 320
                    }
                },
                "title": "10 VIDEOJUEGOS muy CRITICADOS pero que HOY SE VEN CON MEJORES OJOS"
            }
        },
        {
            "etag": "Lw_1ots4pYQGYoNl8uCIxhCu2OU",
            "id": {
                "kind": "youtube#video",
                "videoId": "0pf0t0BrVuE"
            },
            "kind": "youtube#searchResult",
            "snippet": {
                "channelId": "UClNSdNAqetoA97IG9zvscow",
                "channelTitle": "La Caverna del Gamer",
                "description": "Juegos y Tarjetas Prepago M\u00e1s Baratas: https://www.eneba.com/es/?af_id=caverna Descarga la APP de Eneba y obt\u00e9n ...",
                "liveBroadcastContent": "none",
                "publishTime": "2023-09-27T16:00:02Z",
                "publishedAt": "2023-09-27T16:00:02Z",
                "thumbnails": {
                    "default": {
                        "height": 90,
                        "url": "https://i.ytimg.com/vi/0pf0t0BrVuE/default.jpg",
                        "width": 120
                    },
                    "high": {
                        "height": 360,
                        "url": "https://i.ytimg.com/vi/0pf0t0BrVuE/hqdefault.jpg",
                        "width": 480
                    },
                    "medium": {
                        "height": 180,
                        "url": "https://i.ytimg.com/vi/0pf0t0BrVuE/mqdefault.jpg",
                        "width": 320
                    }
                },
                "title": "10 VIDEOJUEGOS que SON TREMENDAMENTE HOSTILES con EL JUGADOR"
            }
        },
        {
            "etag": "n-2A9VgdA8QB6lFWsktTR_0JgzM",
            "id": {
                "kind": "youtube#video",
                "videoId": "SMhlqV4n2dg"
            },
            "kind": "youtube#searchResult",
            "snippet": {
                "channelId": "UCUl-2o1dLbH_GCoU_B_1tsg",
                "channelTitle": "Luan Palomera",
                "description": "Juega a World of Warships aqu\u00ed \u25bb https://wo.ws/3DqmV0c \u00a1Gracias a World of Warships por patrocinar este v\u00eddeo! Durante el ...",
                "liveBroadcastContent": "none",
                "publishTime": "2022-11-11T21:36:12Z",
                "publishedAt": "2022-11-11T21:36:12Z",
                "thumbnails": {
                    "default": {
                        "height": 90,
                        "url": "https://i.ytimg.com/vi/SMhlqV4n2dg/default.jpg",
                        "width": 120
                    },
                    "high": {
                        "height": 360,
                        "url": "https://i.ytimg.com/vi/SMhlqV4n2dg/hqdefault.jpg",
                        "width": 480
                    },
                    "medium": {
                        "height": 180,
                        "url": "https://i.ytimg.com/vi/SMhlqV4n2dg/mqdefault.jpg",
                        "width": 320
                    }
                },
                "title": "10 Videojuegos PIRATA que EST\u00c1N PARA LLORAR (de la risa!) \ud83c\udfae\ud83e\udd23 | PARTE 3"
            }
        },
        {
            "etag": "5tzj0DXd0IAMuFudhnGf5zT1nFs",
            "id": {
                "kind": "youtube#video",
                "videoId": "fGHA__NV-FM"
            },
            "kind": "youtube#searchResult",
            "snippet": {
                "channelId": "UClNSdNAqetoA97IG9zvscow",
                "channelTitle": "La Caverna del Gamer",
                "description": "Juegos y Tarjetas Prepago M\u00e1s Baratas: https://www.eneba.com/es/?af_id=caverna Descarga la APP de Eneba y vende ...",
                "liveBroadcastContent": "none",
                "publishTime": "2023-06-14T16:00:26Z",
                "publishedAt": "2023-06-14T16:00:26Z",
                "thumbnails": {
                    "default": {
                        "height": 90,
                        "url": "https://i.ytimg.com/vi/fGHA__NV-FM/default.jpg",
                        "width": 120
                    },
                    "high": {
                        "height": 360,
                        "url": "https://i.ytimg.com/vi/fGHA__NV-FM/hqdefault.jpg",
                        "width": 480
                    },
                    "medium": {
                        "height": 180,
                        "url": "https://i.ytimg.com/vi/fGHA__NV-FM/mqdefault.jpg",
                        "width": 320
                    }
                },
                "title": "10 VIDEOJUEGOS que FUERON RESTAURADOS o RECUPERADOS por LA COMUNIDAD"
            }
        },
        {
            "etag": "zrc96-aFecSzGSLBRUifTdKwdBU",
            "id": {
                "kind": "youtube#video",
                "videoId": "v1cbIZGy-Es"
            },
            "kind": "youtube#searchResult",
            "snippet": {
                "channelId": "UCeSb0pP7FfQYE7wFFIQW-VQ",
                "channelTitle": "John Falz",
                "description": "Hoy Sonic.Exe de sonic me ha atrapado en una habitaci\u00f3n con 100 Botones misteriosos en minecraft de videojuegos (sonic, five ...",
                "liveBroadcastContent": "none",
                "publishTime": "2023-02-23T04:01:00Z",
                "publishedAt": "2023-02-23T04:01:00Z",
                "thumbnails": {
                    "default": {
                        "height": 90,
                        "url": "https://i.ytimg.com/vi/v1cbIZGy-Es/default.jpg",
                        "width": 120
                    },
                    "high": {
                        "height": 360,
                        "url": "https://i.ytimg.com/vi/v1cbIZGy-Es/hqdefault.jpg",
                        "width": 480
                    },
                    "medium": {
                        "height": 180,
                        "url": "https://i.ytimg.com/vi/v1cbIZGy-Es/mqdefault.jpg",
                        "width": 320
                    }
                },
                "title": "\u00a1100 Botones De Videojuegos Solo 1 Para Escapar! \ud83c\udfae\ud83d\udd34\ud83d\ude31"
            }
        },
        {
            "etag": "FteYgxl_uqaDALaBcWgMRfpRvTg",
            "id": {
                "kind": "youtube#video",
                "videoId": "yASCAzbwr9g"
            },
            "kind": "youtube#searchResult",
            "snippet": {
                "channelId": "UC8qwp8wffpDN7Lak3Hu6c3g",
                "channelTitle": "Polo Guerrero",
                "description": "Nos han dicho muchas veces que los videojuegos son malos o hacen da\u00f1o a nuestra salud. Pero \u00bfRealmente son malos?",
                "liveBroadcastContent": "none",
                "publishTime": "2022-03-07T23:34:25Z",
                "publishedAt": "2022-03-07T23:34:25Z",
                "thumbnails": {
                    "default": {
                        "height": 90,
                        "url": "https://i.ytimg.com/vi/yASCAzbwr9g/default.jpg",
                        "width": 120
                    },
                    "high": {
                        "height": 360,
                        "url": "https://i.ytimg.com/vi/yASCAzbwr9g/hqdefault.jpg",
                        "width": 480
                    },
                    "medium": {
                        "height": 180,
                        "url": "https://i.ytimg.com/vi/yASCAzbwr9g/mqdefault.jpg",
                        "width": 320
                    }
                },
                "title": "12 COSAS QUE DEBES SABER SOBRE LOS VIDEOJUEGOS | Polo Guerrero"
            }
        },
        {
            "etag": "9kNfwwsg3u3ZHKsEGIlx9b77cxM",
            "id": {
                "kind": "youtube#video",
                "videoId": "qvhb83Ty_wY"
            },
            "kind": "youtube#searchResult",
            "snippet": {
                "channelId": "UCXoPy1Q1G39fCemCMAmiorQ",
                "channelTitle": "Zico Tops",
                "description": "Descarga Honkai: Star Rail https://hoyo.link/d1UwCpAd y prueba a Silver Wolf, la hacker genio que puede alterar la realidad!",
                "liveBroadcastContent": "none",
                "publishTime": "2023-06-11T00:36:28Z",
                "publishedAt": "2023-06-11T00:36:28Z",
                "thumbnails": {
                    "default": {
                        "height": 90,
                        "url": "https://i.ytimg.com/vi/qvhb83Ty_wY/default.jpg",
                        "width": 120
                    },
                    "high": {
                        "height": 360,
                        "url": "https://i.ytimg.com/vi/qvhb83Ty_wY/hqdefault.jpg",
                        "width": 480
                    },
                    "medium": {
                        "height": 180,
                        "url": "https://i.ytimg.com/vi/qvhb83Ty_wY/mqdefault.jpg",
                        "width": 320
                    }
                },
                "title": "14 Finales de Videojuegos que Casi Nadie ha Visto"
            }
        },
        {
            "etag": "x7eSyYwhDIv4ji1o_OwwKSWIkJk",
            "id": {
                "kind": "youtube#video",
                "videoId": "OdnHoThPU1g"
            },
            "kind": "youtube#searchResult",
            "snippet": {
                "channelId": "UCq_oSgHK9lk6NUUgkhUOPnw",
                "channelTitle": "DeToxoMoroxo",
                "description": "Obsidiana en La Vida Real | 15 Cosas que NO SAB\u00cdAS De Los videojuegos #3 \u25b6\ufe0fSuscr\u00edbete y activa la ...",
                "liveBroadcastContent": "none",
                "publishTime": "2023-03-07T22:25:08Z",
                "publishedAt": "2023-03-07T22:25:08Z",
                "thumbnails": {
                    "default": {
                        "height": 90,
                        "url": "https://i.ytimg.com/vi/OdnHoThPU1g/default.jpg",
                        "width": 120
                    },
                    "high": {
                        "height": 360,
                        "url": "https://i.ytimg.com/vi/OdnHoThPU1g/hqdefault.jpg",
                        "width": 480
                    },
                    "medium": {
                        "height": 180,
                        "url": "https://i.ytimg.com/vi/OdnHoThPU1g/mqdefault.jpg",
                        "width": 320
                    }
                },
                "title": "15 Cosas que NO SAB\u00cdAS De Los Videojuegos #3 \ud83d\ude32\ud83c\udfae| DeToxoMoroxo"
            }
        },
        {
            "etag": "WoeJaSQj9pqHtAI1KJzssggD3-U",
            "id": {
                "kind": "youtube#video",
                "videoId": "oUP3uHTUa98"
            },
            "kind": "youtube#searchResult",
            "snippet": {
                "channelId": "UCzRKnN3Si8tawp35-Ilvqng",
                "channelTitle": "El Gamer Friki",
                "description": "Convi\u00e9rtete en miembro de este canal para disfrutar de ventajas: ...",
                "liveBroadcastContent": "none",
                "publishTime": "2023-04-24T05:05:13Z",
                "publishedAt": "2023-04-24T05:05:13Z",
                "thumbnails": {
                    "default": {
                        "height": 90,
                        "url": "https://i.ytimg.com/vi/oUP3uHTUa98/default.jpg",
                        "width": 120
                    },
                    "high": {
                        "height": 360,
                        "url": "https://i.ytimg.com/vi/oUP3uHTUa98/hqdefault.jpg",
                        "width": 480
                    },
                    "medium": {
                        "height": 180,
                        "url": "https://i.ytimg.com/vi/oUP3uHTUa98/mqdefault.jpg",
                        "width": 320
                    }
                },
                "title": "15 Curiosidades de los Videojuegos Parte 40"
            }
        },
        {
            "etag": "NgQQ7yz4DIttZegzLYQ0u-OYdiU",
            "id": {
                "kind": "youtube#video",
                "videoId": "Kj3v-x-L2wo"
            },
            "kind": "youtube#searchResult",
            "snippet": {
                "channelId": "UCXoPy1Q1G39fCemCMAmiorQ",
                "channelTitle": "Zico Tops",
                "description": "Acompa\u00f1ame a resolver M\u00c1S misterios en tus juegos favoritos, y conoce sus respuestas incre\u00edbles! Suscribete a Zico Tops para ...",
                "liveBroadcastContent": "none",
                "publishTime": "2022-05-16T21:00:16Z",
                "publishedAt": "2022-05-16T21:00:16Z",
                "thumbnails": {
                    "default": {
                        "height": 90,
                        "url": "https://i.ytimg.com/vi/Kj3v-x-L2wo/default.jpg",
                        "width": 120
                    },
                    "high": {
                        "height": 360,
                        "url": "https://i.ytimg.com/vi/Kj3v-x-L2wo/hqdefault.jpg",
                        "width": 480
                    },
                    "medium": {
                        "height": 180,
                        "url": "https://i.ytimg.com/vi/Kj3v-x-L2wo/mqdefault.jpg",
                        "width": 320
                    }
                },
                "title": "2\u00aa Temporada &quot;Misterios de Videojuegos Resueltos de una vez por Todas&quot;"
            }
        },
        {
            "etag": "jAyU7Ay2jrfF7ojc49zpcbb8PJ8",
            "id": {
                "kind": "youtube#video",
                "videoId": "ZnPMzjmsRIo"
            },
            "kind": "youtube#searchResult",
            "snippet": {
                "channelId": "UCqBAbqbx4q7G5upsptccdPA",
                "channelTitle": "Pepe El Mago",
                "description": "Listo para descubrir La 2\u00aa Temporada: Videojuegos Felices con Historias de Fondo Espeluznantes? Acomp\u00e1\u00f1ame en este top!",
                "liveBroadcastContent": "none",
                "publishTime": "2023-04-12T19:39:17Z",
                "publishedAt": "2023-04-12T19:39:17Z",
                "thumbnails": {
                    "default": {
                        "height": 90,
                        "url": "https://i.ytimg.com/vi/ZnPMzjmsRIo/default.jpg",
                        "width": 120
                    },
                    "high": {
                        "height": 360,
                        "url": "https://i.ytimg.com/vi/ZnPMzjmsRIo/hqdefault.jpg",
                        "width": 480
                    },
                    "medium": {
                        "height": 180,
                        "url": "https://i.ytimg.com/vi/ZnPMzjmsRIo/mqdefault.jpg",
                        "width": 320
                    }
                },
                "title": "2\u00aa Temporada: Videojuegos Felices con Historias de Fondo Espeluznantes"
            }
        },
        {
            "etag": "0oUntpftYEyoyuEnTDWFCvWfNhA",
            "id": {
                "kind": "youtube#video",
                "videoId": "uRpBOpstDxQ"
            },
            "kind": "youtube#searchResult",
            "snippet": {
                "channelId": "UCyDtiW8ETQs6tf2L3AEL5uw",
                "channelTitle": "Cuadradito y Circulito Vlogs",
                "description": "24 HORAS EN VIDEOJUEGOS \ud83d\udd79\ufe0f | Cuadradito y Circulito Vlogs realizar\u00e1n el desaf\u00edo de las 24 hs no en uno, sino en varios ...",
                "liveBroadcastContent": "none",
                "publishTime": "2022-12-07T16:30:13Z",
                "publishedAt": "2022-12-07T16:30:13Z",
                "thumbnails": {
                    "default": {
                        "height": 90,
                        "url": "https://i.ytimg.com/vi/uRpBOpstDxQ/default.jpg",
                        "width": 120
                    },
                    "high": {
                        "height": 360,
                        "url": "https://i.ytimg.com/vi/uRpBOpstDxQ/hqdefault.jpg",
                        "width": 480
                    },
                    "medium": {
                        "height": 180,
                        "url": "https://i.ytimg.com/vi/uRpBOpstDxQ/mqdefault.jpg",
                        "width": 320
                    }
                },
                "title": "24 HORAS EN VIDEOJUEGOS \ud83d\udd79\ufe0f | Cuadradito y Circulito Vlogs"
            }
        },
        {
            "etag": "xv1DpVglZZz9Yyv5oCqVhc_nwd8",
            "id": {
                "kind": "youtube#video",
                "videoId": "VK2OiD-UN1E"
            },
            "kind": "youtube#searchResult",
            "snippet": {
                "channelId": "UCqma_8hr8yOgr37wdUY-E7Q",
                "channelTitle": "NANDO",
                "description": "24 videojuegos en la vida real en 24 horas... S\u00edguenos en Instagram: NANDO: https://www.instagram.com/nandoweee YOLO: ...",
                "liveBroadcastContent": "none",
                "publishTime": "2022-10-21T20:45:26Z",
                "publishedAt": "2022-10-21T20:45:26Z",
                "thumbnails": {
                    "default": {
                        "height": 90,
                        "url": "https://i.ytimg.com/vi/VK2OiD-UN1E/default.jpg",
                        "width": 120
                    },
                    "high": {
                        "height": 360,
                        "url": "https://i.ytimg.com/vi/VK2OiD-UN1E/hqdefault.jpg",
                        "width": 480
                    },
                    "medium": {
                        "height": 180,
                        "url": "https://i.ytimg.com/vi/VK2OiD-UN1E/mqdefault.jpg",
                        "width": 320
                    }
                },
                "title": "24 VIDEOJUEGOS EN LA VIDA REAL EN 24 HORAS!!"
            }
        },
        {
            "etag": "TEmIezuo1TQof_8y9U2SSiIcth0",
            "id": {
                "kind": "youtube#video",
                "videoId": "PPYzHVMt8kI"
            },
            "kind": "youtube#searchResult",
            "snippet": {
                "channelId": "UCItB-CuaySFsWKw-7mSajQg",
                "channelTitle": "FamilyTube",
                "description": "Hoy nos enfrentamos al divertido reto de Jugar 24 horas a videojuegos y videoconsolas retro de los a\u00f1os 80 y 90. Nes, Master ...",
                "liveBroadcastContent": "none",
                "publishTime": "2021-04-28T18:00:12Z",
                "publishedAt": "2021-04-28T18:00:12Z",
                "thumbnails": {
                    "default": {
                        "height": 90,
                        "url": "https://i.ytimg.com/vi/PPYzHVMt8kI/default.jpg",
                        "width": 120
                    },
                    "high": {
                        "height": 360,
                        "url": "https://i.ytimg.com/vi/PPYzHVMt8kI/hqdefault.jpg",
                        "width": 480
                    },
                    "medium": {
                        "height": 180,
                        "url": "https://i.ytimg.com/vi/PPYzHVMt8kI/mqdefault.jpg",
                        "width": 320
                    }
                },
                "title": "24h Jugando Videojuegos Retro"
            }
        },
        {
            "etag": "QEjT-NEzFO_PK2WhJTmu9fOiqfA",
            "id": {
                "kind": "youtube#video",
                "videoId": "DutJLsoA4aw"
            },
            "kind": "youtube#searchResult",
            "snippet": {
                "channelId": "UCItB-CuaySFsWKw-7mSajQg",
                "channelTitle": "FamilyTube",
                "description": "Hoy jugamos toda nuestra colecci\u00f3n PlayStation desde la primera PS one en un divertido reto 24 horas jugando con los ...",
                "liveBroadcastContent": "none",
                "publishTime": "2021-05-08T18:00:15Z",
                "publishedAt": "2021-05-08T18:00:15Z",
                "thumbnails": {
                    "default": {
                        "height": 90,
                        "url": "https://i.ytimg.com/vi/DutJLsoA4aw/default.jpg",
                        "width": 120
                    },
                    "high": {
                        "height": 360,
                        "url": "https://i.ytimg.com/vi/DutJLsoA4aw/hqdefault.jpg",
                        "width": 480
                    },
                    "medium": {
                        "height": 180,
                        "url": "https://i.ytimg.com/vi/DutJLsoA4aw/mqdefault.jpg",
                        "width": 320
                    }
                },
                "title": "24h Jugando Videojuegos PS"
            }
        },
        {
            "etag": "JQdtqstEyAmQHfxkrMECYBTzJLw",
            "id": {
                "kind": "youtube#video",
                "videoId": "wa4a40lC6GY"
            },
            "kind": "youtube#searchResult",
            "snippet": {
                "channelId": "UCzvJ2IoBfwqOoJfbD4Tqdzw",
                "channelTitle": "Kenndy Leo",
                "description": "",
                "liveBroadcastContent": "none",
                "publishTime": "2023-05-18T23:58:00Z",
                "publishedAt": "2023-05-18T23:58:00Z",
                "thumbnails": {
                    "default": {
                        "height": 90,
                        "url": "https://i.ytimg.com/vi/wa4a40lC6GY/default.jpg",
                        "width": 120
                    },
                    "high": {
                        "height": 360,
                        "url": "https://i.ytimg.com/vi/wa4a40lC6GY/hqdefault.jpg",
                        "width": 480
                    },
                    "medium": {
                        "height": 180,
                        "url": "https://i.ytimg.com/vi/wa4a40lC6GY/mqdefault.jpg",
                        "width": 320
                    }
                },
                "title": "3 Curiosidades de Left 4 Dead #videojuegos #gaming #l4d #viral #shortsviral #gameplay"
            }
        },
        {
            "etag": "uw_OGoi4XQsGTzK5NOIRXttuQSk",
            "id": {
                "kind": "youtube#video",
                "videoId": "GfdxzbJ8yTo"
            },
            "kind": "youtube#searchResult",
            "snippet": {
                "channelId": "UCYiGq8XF7YQD00x7wAd62Zg",
                "channelTitle": "JuegaGerman",
                "description": "Gracias Opera por patroninar este video, descarga Opera aqui para tu compu, si no pones de fondo el calvo musculoso con ...",
                "liveBroadcastContent": "none",
                "publishTime": "2023-06-01T16:42:30Z",
                "publishedAt": "2023-06-01T16:42:30Z",
                "thumbnails": {
                    "default": {
                        "height": 90,
                        "url": "https://i.ytimg.com/vi/GfdxzbJ8yTo/default.jpg",
                        "width": 120
                    },
                    "high": {
                        "height": 360,
                        "url": "https://i.ytimg.com/vi/GfdxzbJ8yTo/hqdefault.jpg",
                        "width": 480
                    },
                    "medium": {
                        "height": 180,
                        "url": "https://i.ytimg.com/vi/GfdxzbJ8yTo/mqdefault.jpg",
                        "width": 320
                    }
                },
                "title": "3 JUEGOS DE TERROR en un video"
            }
        },
        {
            "etag": "hplVkQ0cCU7t9stv-iAvYx4jMZ4",
            "id": {
                "kind": "youtube#video",
                "videoId": "NLVa_3qzOek"
            },
            "kind": "youtube#searchResult",
            "snippet": {
                "channelId": "UCqBAbqbx4q7G5upsptccdPA",
                "channelTitle": "Pepe El Mago",
                "description": "Listo para descubrir 4 Videojuegos Felices con Historias de Fondo Espeluznantes? Acomp\u00e1\u00f1ame en este top! PARTES ...",
                "liveBroadcastContent": "none",
                "publishTime": "2023-10-06T17:16:53Z",
                "publishedAt": "2023-10-06T17:16:53Z",
                "thumbnails": {
                    "default": {
                        "height": 90,
                        "url": "https://i.ytimg.com/vi/NLVa_3qzOek/default.jpg",
                        "width": 120
                    },
                    "high": {
                        "height": 360,
                        "url": "https://i.ytimg.com/vi/NLVa_3qzOek/hqdefault.jpg",
                        "width": 480
                    },
                    "medium": {
                        "height": 180,
                        "url": "https://i.ytimg.com/vi/NLVa_3qzOek/mqdefault.jpg",
                        "width": 320
                    }
                },
                "title": "3 Videojuegos Felices con Historias de Fondo Espeluznantes (PARTE 8) - Pepe el Mago"
            }
        },
        {
            "etag": "NEbBfQgXd7H1a6Cz88gwP0Ojjz8",
            "id": {
                "kind": "youtube#video",
                "videoId": "vrrySqRXWPc"
            },
            "kind": "youtube#searchResult",
            "snippet": {
                "channelId": "UCohF4xaHv0lr_X09k4nXbqQ",
                "channelTitle": "DrMuuk",
                "description": "SABIAS QUE EXISTEN MUCHOS BENEFICIOS AL JUGAR #videogames Hola mi nombre es DrMuuk este canal esta dedicado ...",
                "liveBroadcastContent": "none",
                "publishTime": "2023-03-30T00:00:19Z",
                "publishedAt": "2023-03-30T00:00:19Z",
                "thumbnails": {
                    "default": {
                        "height": 90,
                        "url": "https://i.ytimg.com/vi/vrrySqRXWPc/default.jpg",
                        "width": 120
                    },
                    "high": {
                        "height": 360,
                        "url": "https://i.ytimg.com/vi/vrrySqRXWPc/hqdefault.jpg",
                        "width": 480
                    },
                    "medium": {
                        "height": 180,
                        "url": "https://i.ytimg.com/vi/vrrySqRXWPc/mqdefault.jpg",
                        "width": 320
                    }
                },
                "title": "5 beneficios SORPRENDENTES de jugar VIDEOJUEGOS | DrMuuk #videojuegos  #videogames #5"
            }
        },
        {
            "etag": "tZrsKe6n6GhQMX8pSMeYk1YI54A",
            "id": {
                "kind": "youtube#video",
                "videoId": "7pREv-voJQw"
            },
            "kind": "youtube#searchResult",
            "snippet": {
                "channelId": "UCbWHdzca49v8J_Qc5_zZYCA",
                "channelTitle": "Mario Amaya94",
                "description": "Si te gust\u00f3 el video no olvides darle al bot\u00f3n de \"me gusta\" y \"suscribirte\", te lo agradecer\u00eda un mont\u00f3n \u00a1Abajo te dejo mis redes ...",
                "liveBroadcastContent": "none",
                "publishTime": "2022-11-12T21:49:06Z",
                "publishedAt": "2022-11-12T21:49:06Z",
                "thumbnails": {
                    "default": {
                        "height": 90,
                        "url": "https://i.ytimg.com/vi/7pREv-voJQw/default.jpg",
                        "width": 120
                    },
                    "high": {
                        "height": 360,
                        "url": "https://i.ytimg.com/vi/7pREv-voJQw/hqdefault.jpg",
                        "width": 480
                    },
                    "medium": {
                        "height": 180,
                        "url": "https://i.ytimg.com/vi/7pREv-voJQw/mqdefault.jpg",
                        "width": 320
                    }
                },
                "title": "5 Curiosidades de #SuperMetroid #SuperNintendo #shorts #videojuegos #retrogames"
            }
        },
        {
            "etag": "TMGABqKvbi2ZtrYlvm5BK2uW4ks",
            "id": {
                "kind": "youtube#video",
                "videoId": "7si9hh1N9DE"
            },
            "kind": "youtube#searchResult",
            "snippet": {
                "channelId": "UCQfURzjSQ4qu7kt9f8_CSPA",
                "channelTitle": "El Camarillo",
                "description": "shorts S\u00edgueme en todas mis Redes Sociales: Instagram: https://www.instagram.com/elelimijo/ TikTok: ...",
                "liveBroadcastContent": "none",
                "publishTime": "2023-06-06T12:00:05Z",
                "publishedAt": "2023-06-06T12:00:05Z",
                "thumbnails": {
                    "default": {
                        "height": 90,
                        "url": "https://i.ytimg.com/vi/7si9hh1N9DE/default.jpg",
                        "width": 120
                    },
                    "high": {
                        "height": 360,
                        "url": "https://i.ytimg.com/vi/7si9hh1N9DE/hqdefault.jpg",
                        "width": 480
                    },
                    "medium": {
                        "height": 180,
                        "url": "https://i.ytimg.com/vi/7si9hh1N9DE/mqdefault.jpg",
                        "width": 320
                    }
                },
                "title": "5 Curiosidades sobre Tecnolog\u00eda en Videojuegos \ud83d\udd79\ufe0f\u2728"
            }
        },
        {
            "etag": "Eav2qqazpUS_DqioQx_YZr_S-HA",
            "id": {
                "kind": "youtube#video",
                "videoId": "d8xd9sXXOQE"
            },
            "kind": "youtube#searchResult",
            "snippet": {
                "channelId": "UCMIBUhL2pb_wPFPoeJ5MWBA",
                "channelTitle": "Julian Abdala",
                "description": "En el d\u00eda de hoy vamos a ver 5 JUEGOS basados en HISTORIAS REALES... Espero que te guste. MIS REDES SOCIALES ...",
                "liveBroadcastContent": "none",
                "publishTime": "2022-12-14T23:45:16Z",
                "publishedAt": "2022-12-14T23:45:16Z",
                "thumbnails": {
                    "default": {
                        "height": 90,
                        "url": "https://i.ytimg.com/vi/d8xd9sXXOQE/default.jpg",
                        "width": 120
                    },
                    "high": {
                        "height": 360,
                        "url": "https://i.ytimg.com/vi/d8xd9sXXOQE/hqdefault.jpg",
                        "width": 480
                    },
                    "medium": {
                        "height": 180,
                        "url": "https://i.ytimg.com/vi/d8xd9sXXOQE/mqdefault.jpg",
                        "width": 320
                    }
                },
                "title": "5 JUEGOS DE TERROR basados en HECHOS REALES"
            }
        },
        {
            "etag": "u9Q-xODSqPc2CnBYuxYLCWuY-zw",
            "id": {
                "kind": "youtube#video",
                "videoId": "iU1RJTsLsWI"
            },
            "kind": "youtube#searchResult",
            "snippet": {
                "channelId": "UCkuPobJMx7DPUdwlVo1TFfA",
                "channelTitle": "Drawblogs",
                "description": "En este video veremos algunos ni\u00f1os que pasaron algunos problemas por culpa de los videojuegos. En esta lista aparecen los ...",
                "liveBroadcastContent": "none",
                "publishTime": "2018-04-08T20:51:40Z",
                "publishedAt": "2018-04-08T20:51:40Z",
                "thumbnails": {
                    "default": {
                        "height": 90,
                        "url": "https://i.ytimg.com/vi/iU1RJTsLsWI/default.jpg",
                        "width": 120
                    },
                    "high": {
                        "height": 360,
                        "url": "https://i.ytimg.com/vi/iU1RJTsLsWI/hqdefault.jpg",
                        "width": 480
                    },
                    "medium": {
                        "height": 180,
                        "url": "https://i.ytimg.com/vi/iU1RJTsLsWI/mqdefault.jpg",
                        "width": 320
                    }
                },
                "title": "5 Ni\u00f1os Arrestados por Culpa de los Videojuegos"
            }
        },
        {
            "etag": "tfrDLReYMghz8p9s-J2S1gsRlqg",
            "id": {
                "kind": "youtube#video",
                "videoId": "3jwSwMY_cDE"
            },
            "kind": "youtube#searchResult",
            "snippet": {
                "channelId": "UCgukmfRfIhfg5K49LSNPslQ",
                "channelTitle": "ThePunkrockergamer",
                "description": "",
                "liveBroadcastContent": "none",
                "publishTime": "2023-05-20T14:55:00Z",
                "publishedAt": "2023-05-20T14:55:00Z",
                "thumbnails": {
                    "default": {
                        "height": 90,
                        "url": "https://i.ytimg.com/vi/3jwSwMY_cDE/default.jpg",
                        "width": 120
                    },
                    "high": {
                        "height": 360,
                        "url": "https://i.ytimg.com/vi/3jwSwMY_cDE/hqdefault.jpg",
                        "width": 480
                    },
                    "medium": {
                        "height": 180,
                        "url": "https://i.ytimg.com/vi/3jwSwMY_cDE/mqdefault.jpg",
                        "width": 320
                    }
                },
                "title": "5 videojuegos de Disney #disney #videojuegos #videogames #gamer #tiktok #fyp"
            }
        },
        {
            "etag": "Ta6BQ9WSsA6xfXfhRsXdKriN-GE",
            "id": {
                "kind": "youtube#video",
                "videoId": "nEX3R0Axcsc"
            },
            "kind": "youtube#searchResult",
            "snippet": {
                "channelId": "UCZz-3Gzf2oXp1nQRDiSrYaw",
                "channelTitle": "Merluso",
                "description": "Descarga gratis Wondershare Filmora12 por aqu\u00ed: http://bit.ly/3RnAu7i Suscr\u00edbete al canal oficial de Filmora por aqu\u00ed: ...",
                "liveBroadcastContent": "none",
                "publishTime": "2023-02-06T21:00:08Z",
                "publishedAt": "2023-02-06T21:00:08Z",
                "thumbnails": {
                    "default": {
                        "height": 90,
                        "url": "https://i.ytimg.com/vi/nEX3R0Axcsc/default.jpg",
                        "width": 120
                    },
                    "high": {
                        "height": 360,
                        "url": "https://i.ytimg.com/vi/nEX3R0Axcsc/hqdefault.jpg",
                        "width": 480
                    },
                    "medium": {
                        "height": 180,
                        "url": "https://i.ytimg.com/vi/nEX3R0Axcsc/mqdefault.jpg",
                        "width": 320
                    }
                },
                "title": "50 Datos INSERVIBLES de VIDEOJUEGOS"
            }
        },
        {
            "etag": "iWxknNLnCFQ2Z88GAs0AOFsdiDk",
            "id": {
                "kind": "youtube#video",
                "videoId": "aXHZhhyjKp4"
            },
            "kind": "youtube#searchResult",
            "snippet": {
                "channelId": "UCzfVXQTP3QVG7kANFyX-lGA",
                "channelTitle": "Dangie Bros en Espa\u00f1ol",
                "description": "Recreamos 50 videojuegos en la vida real durante 50 horas! Recreamos los juegos m\u00e1s populares, ic\u00f3nicos, y divertidos ...",
                "liveBroadcastContent": "none",
                "publishTime": "2022-11-24T16:30:00Z",
                "publishedAt": "2022-11-24T16:30:00Z",
                "thumbnails": {
                    "default": {
                        "height": 90,
                        "url": "https://i.ytimg.com/vi/aXHZhhyjKp4/default.jpg",
                        "width": 120
                    },
                    "high": {
                        "height": 360,
                        "url": "https://i.ytimg.com/vi/aXHZhhyjKp4/hqdefault.jpg",
                        "width": 480
                    },
                    "medium": {
                        "height": 180,
                        "url": "https://i.ytimg.com/vi/aXHZhhyjKp4/mqdefault.jpg",
                        "width": 320
                    }
                },
                "title": "50 VIDEOJUEGOS en La Vida Real"
            }
        },
        {
            "etag": "yddvngrMcapNOYoJoJP3lvKfqZ8",
            "id": {
                "kind": "youtube#video",
                "videoId": "Lbsazwfodnw"
            },
            "kind": "youtube#searchResult",
            "snippet": {
                "channelId": "UCcUcfEwyDXBMsvYfoOdK7SA",
                "channelTitle": "Alex PH",
                "description": "6 creepypastas de videojuegos: En este video veras cosas aterradoras, mitos oscuros, descubrimientos extra\u00f1os y otros misterios ...",
                "liveBroadcastContent": "none",
                "publishTime": "2022-06-17T19:00:07Z",
                "publishedAt": "2022-06-17T19:00:07Z",
                "thumbnails": {
                    "default": {
                        "height": 90,
                        "url": "https://i.ytimg.com/vi/Lbsazwfodnw/default.jpg",
                        "width": 120
                    },
                    "high": {
                        "height": 360,
                        "url": "https://i.ytimg.com/vi/Lbsazwfodnw/hqdefault.jpg",
                        "width": 480
                    },
                    "medium": {
                        "height": 180,
                        "url": "https://i.ytimg.com/vi/Lbsazwfodnw/mqdefault.jpg",
                        "width": 320
                    }
                },
                "title": "6 Creepypastas De Videojuegos"
            }
        },
        {
            "etag": "7RrzIZcuvvIWRm3ScOfGODtXYzg",
            "id": {
                "kind": "youtube#video",
                "videoId": "rwxkbpuvA-o"
            },
            "kind": "youtube#searchResult",
            "snippet": {
                "channelId": "UCflbkEi1rc0c7yWTqp9g8Gg",
                "channelTitle": "PERITA",
                "description": "hoy salimos de ruta de cazas de videojuegos donde en tiempos pasados era posible la caza de buenos precios de videojuegos ...",
                "liveBroadcastContent": "none",
                "publishTime": "2022-06-24T18:13:19Z",
                "publishedAt": "2022-06-24T18:13:19Z",
                "thumbnails": {
                    "default": {
                        "height": 90,
                        "url": "https://i.ytimg.com/vi/rwxkbpuvA-o/default.jpg",
                        "width": 120
                    },
                    "high": {
                        "height": 360,
                        "url": "https://i.ytimg.com/vi/rwxkbpuvA-o/hqdefault.jpg",
                        "width": 480
                    },
                    "medium": {
                        "height": 180,
                        "url": "https://i.ytimg.com/vi/rwxkbpuvA-o/mqdefault.jpg",
                        "width": 320
                    }
                },
                "title": "6 TIENDAS de VIDEOJUEGOS en 2 HORAS (CAZAREMOS ALGO?)"
            }
        },
        {
            "etag": "TkKo-e4HjEvurylibC0m-YWZcs4",
            "id": {
                "kind": "youtube#video",
                "videoId": "fZgt3pqxsac"
            },
            "kind": "youtube#searchResult",
            "snippet": {
                "channelId": "UCjMtc3v7g-jrAquecbt7OyA",
                "channelTitle": "Hiper",
                "description": "C\u00f3digo de Creador en Fortnite/Epic: HIPER-YOUTUBE Hazte miembro del canal: https://www.youtube.com/c/hiperop/join ...",
                "liveBroadcastContent": "none",
                "publishTime": "2022-08-29T21:13:39Z",
                "publishedAt": "2022-08-29T21:13:39Z",
                "thumbnails": {
                    "default": {
                        "height": 90,
                        "url": "https://i.ytimg.com/vi/fZgt3pqxsac/default.jpg",
                        "width": 120
                    },
                    "high": {
                        "height": 360,
                        "url": "https://i.ytimg.com/vi/fZgt3pqxsac/hqdefault.jpg",
                        "width": 480
                    },
                    "medium": {
                        "height": 180,
                        "url": "https://i.ytimg.com/vi/fZgt3pqxsac/mqdefault.jpg",
                        "width": 320
                    }
                },
                "title": "60 REFERENCIAS A VIDEOJUEGOS EN FORTNITE"
            }
        },
        {
            "etag": "MSNwWSm0vfsUuzWRIt6vqij-01w",
            "id": {
                "kind": "youtube#video",
                "videoId": "QqQgN28bCeE"
            },
            "kind": "youtube#searchResult",
            "snippet": {
                "channelId": "UCq_oSgHK9lk6NUUgkhUOPnw",
                "channelTitle": "DeToxoMoroxo",
                "description": "7 Cosas SECRETAS En Videojuegos Que NO DEBIAN Ser ENCONTRADAS | DeToxoMoroxo Canal de Resumenes El Tio ...",
                "liveBroadcastContent": "none",
                "publishTime": "2022-02-07T22:13:35Z",
                "publishedAt": "2022-02-07T22:13:35Z",
                "thumbnails": {
                    "default": {
                        "height": 90,
                        "url": "https://i.ytimg.com/vi/QqQgN28bCeE/default.jpg",
                        "width": 120
                    },
                    "high": {
                        "height": 360,
                        "url": "https://i.ytimg.com/vi/QqQgN28bCeE/hqdefault.jpg",
                        "width": 480
                    },
                    "medium": {
                        "height": 180,
                        "url": "https://i.ytimg.com/vi/QqQgN28bCeE/mqdefault.jpg",
                        "width": 320
                    }
                },
                "title": "7 Cosas SECRETAS En Videojuegos Que NO DEBIAN Ser ENCONTRADAS \ud83d\ude32\ud83c\udfae | DeToxoMoroxo"
            }
        },
        {
            "etag": "SGR9pmGDYD42PSeCQzTPkdCs9VU",
            "id": {
                "kind": "youtube#video",
                "videoId": "JfUmtAKaT1I"
            },
            "kind": "youtube#searchResult",
            "snippet": {
                "channelId": "UCXoPy1Q1G39fCemCMAmiorQ",
                "channelTitle": "Zico Tops",
                "description": "En este Top conocer\u00e1s trolleadas \u00e9picas por hackers y tramposos en los juegos, que resultaron en desastres incre\u00edbles.",
                "liveBroadcastContent": "none",
                "publishTime": "2020-08-11T01:09:53Z",
                "publishedAt": "2020-08-11T01:09:53Z",
                "thumbnails": {
                    "default": {
                        "height": 90,
                        "url": "https://i.ytimg.com/vi/JfUmtAKaT1I/default.jpg",
                        "width": 120
                    },
                    "high": {
                        "height": 360,
                        "url": "https://i.ytimg.com/vi/JfUmtAKaT1I/hqdefault.jpg",
                        "width": 480
                    },
                    "medium": {
                        "height": 180,
                        "url": "https://i.ytimg.com/vi/JfUmtAKaT1I/mqdefault.jpg",
                        "width": 320
                    }
                },
                "title": "7 Hackers de Videojuegos que Causaron Grandes Desastres"
            }
        },
        {
            "etag": "W8RhHpLZ_VGjFoVkpjUq1IRFydY",
            "id": {
                "kind": "youtube#video",
                "videoId": "6Hr1ng8LDxo"
            },
            "kind": "youtube#searchResult",
            "snippet": {
                "channelId": "UCXoPy1Q1G39fCemCMAmiorQ",
                "channelTitle": "Zico Tops",
                "description": "En este Top 7 ver\u00e1s como se hacen descubrimientos y logros \u00e9picos en tus juegos favoritos, que requieren de gran paciencia y ...",
                "liveBroadcastContent": "none",
                "publishTime": "2023-03-26T00:44:21Z",
                "publishedAt": "2023-03-26T00:44:21Z",
                "thumbnails": {
                    "default": {
                        "height": 90,
                        "url": "https://i.ytimg.com/vi/6Hr1ng8LDxo/default.jpg",
                        "width": 120
                    },
                    "high": {
                        "height": 360,
                        "url": "https://i.ytimg.com/vi/6Hr1ng8LDxo/hqdefault.jpg",
                        "width": 480
                    },
                    "medium": {
                        "height": 180,
                        "url": "https://i.ytimg.com/vi/6Hr1ng8LDxo/mqdefault.jpg",
                        "width": 320
                    }
                },
                "title": "7 Haza\u00f1as de Videojuegos tan Incre\u00edbles que Parecen Imposibles #9"
            }
        },
        {
            "etag": "MOea5WCBmM_l-yX8gR1Z5Flqmo4",
            "id": {
                "kind": "youtube#video",
                "videoId": "gSI1KjdJk5w"
            },
            "kind": "youtube#searchResult",
            "snippet": {
                "channelId": "UCXoPy1Q1G39fCemCMAmiorQ",
                "channelTitle": "Zico Tops",
                "description": "Descarga GRATIS Wondershare Filmora por aqu\u00ed: https://bit.ly/3wBEo39 Descarga gratis Wondershare FilmoraGo por aqu\u00ed: ...",
                "liveBroadcastContent": "none",
                "publishTime": "2022-09-04T00:12:01Z",
                "publishedAt": "2022-09-04T00:12:01Z",
                "thumbnails": {
                    "default": {
                        "height": 90,
                        "url": "https://i.ytimg.com/vi/gSI1KjdJk5w/default.jpg",
                        "width": 120
                    },
                    "high": {
                        "height": 360,
                        "url": "https://i.ytimg.com/vi/gSI1KjdJk5w/hqdefault.jpg",
                        "width": 480
                    },
                    "medium": {
                        "height": 180,
                        "url": "https://i.ytimg.com/vi/gSI1KjdJk5w/mqdefault.jpg",
                        "width": 320
                    }
                },
                "title": "7 Haza\u00f1as de Videojuegos tan Incre\u00edbles que Parecen Imposibles #8"
            }
        },
        {
            "etag": "ZYIMIYrcbOHPY76zNdXwOQp1eQs",
            "id": {
                "kind": "youtube#video",
                "videoId": "dA8QBNloins"
            },
            "kind": "youtube#searchResult",
            "snippet": {
                "channelId": "UCXoPy1Q1G39fCemCMAmiorQ",
                "channelTitle": "Zico Tops",
                "description": "\u00danete a la diversi\u00f3n en Dungeon Fighter Online: https://ggcont.me/3ZfHVAE Usa el cup\u00f3n \"WELC-OMET-ODFO-GIFT\" para ...",
                "liveBroadcastContent": "none",
                "publishTime": "2023-03-03T00:06:00Z",
                "publishedAt": "2023-03-03T00:06:00Z",
                "thumbnails": {
                    "default": {
                        "height": 90,
                        "url": "https://i.ytimg.com/vi/dA8QBNloins/default.jpg",
                        "width": 120
                    },
                    "high": {
                        "height": 360,
                        "url": "https://i.ytimg.com/vi/dA8QBNloins/hqdefault.jpg",
                        "width": 480
                    },
                    "medium": {
                        "height": 180,
                        "url": "https://i.ytimg.com/vi/dA8QBNloins/mqdefault.jpg",
                        "width": 320
                    }
                },
                "title": "7 Misterios de Videojuegos Resueltos de una vez por Todas (PARTE 12)"
            }
        },
        {
            "etag": "3WmmebEKxUdoiEi1kiGS16ep-4M",
            "id": {
                "kind": "youtube#video",
                "videoId": "1uM2k-Wo3u8"
            },
            "kind": "youtube#searchResult",
            "snippet": {
                "channelId": "UCq_oSgHK9lk6NUUgkhUOPnw",
                "channelTitle": "DeToxoMoroxo",
                "description": "Descarga el Juego: https://mhy.link/994FGGA6 Monstruos MAS GRANDES De Los VIDEOJUEGOS: Cronos (Kronos) / GOW ...",
                "liveBroadcastContent": "none",
                "publishTime": "2021-07-22T18:22:53Z",
                "publishedAt": "2021-07-22T18:22:53Z",
                "thumbnails": {
                    "default": {
                        "height": 90,
                        "url": "https://i.ytimg.com/vi/1uM2k-Wo3u8/default.jpg",
                        "width": 120
                    },
                    "high": {
                        "height": 360,
                        "url": "https://i.ytimg.com/vi/1uM2k-Wo3u8/hqdefault.jpg",
                        "width": 480
                    },
                    "medium": {
                        "height": 180,
                        "url": "https://i.ytimg.com/vi/1uM2k-Wo3u8/mqdefault.jpg",
                        "width": 320
                    }
                },
                "title": "7 Monstruos MAS GRANDES De Los VIDEOJUEGOS | DeToxoMoroxo"
            }
        },
        {
            "etag": "jNJKZwL7SIRpfUeXAOiXOVK-uks",
            "id": {
                "kind": "youtube#video",
                "videoId": "QDw3Tp7pVzw"
            },
            "kind": "youtube#searchResult",
            "snippet": {
                "channelId": "UC44pgC5JxSFX0IJIC4K4kUQ",
                "channelTitle": "Armapedia",
                "description": "Conoce nuevos videojuegos que me han dejado impactado, ya sea por sus gr\u00e1ficas, o su historia o sus mec\u00e1nicas de juego.",
                "liveBroadcastContent": "none",
                "publishTime": "2021-12-20T22:04:33Z",
                "publishedAt": "2021-12-20T22:04:33Z",
                "thumbnails": {
                    "default": {
                        "height": 90,
                        "url": "https://i.ytimg.com/vi/QDw3Tp7pVzw/default.jpg",
                        "width": 120
                    },
                    "high": {
                        "height": 360,
                        "url": "https://i.ytimg.com/vi/QDw3Tp7pVzw/hqdefault.jpg",
                        "width": 480
                    },
                    "medium": {
                        "height": 180,
                        "url": "https://i.ytimg.com/vi/QDw3Tp7pVzw/mqdefault.jpg",
                        "width": 320
                    }
                },
                "title": "7 NUEVOS Videojuegos Militares y T\u00e1cticos Realistas"
            }
        },
        {
            "etag": "dcH5HSuhRyHYtSuzI76iweTYfXg",
            "id": {
                "kind": "youtube#video",
                "videoId": "27DJ2cqV-os"
            },
            "kind": "youtube#searchResult",
            "snippet": {
                "channelId": "UCXoPy1Q1G39fCemCMAmiorQ",
                "channelTitle": "Zico Tops",
                "description": "En este Top 7 ver\u00e1s las maneras mas extra\u00f1as y absurdas de vencer y destruir a los jefes de tus aventuras favoritas, se ira ...",
                "liveBroadcastContent": "none",
                "publishTime": "2023-04-24T22:04:23Z",
                "publishedAt": "2023-04-24T22:04:23Z",
                "thumbnails": {
                    "default": {
                        "height": 90,
                        "url": "https://i.ytimg.com/vi/27DJ2cqV-os/default.jpg",
                        "width": 120
                    },
                    "high": {
                        "height": 360,
                        "url": "https://i.ytimg.com/vi/27DJ2cqV-os/hqdefault.jpg",
                        "width": 480
                    },
                    "medium": {
                        "height": 180,
                        "url": "https://i.ytimg.com/vi/27DJ2cqV-os/mqdefault.jpg",
                        "width": 320
                    }
                },
                "title": "7 Trucos Rid\u00edculos para Derrotar a Jefes de Videojuegos"
            }
        },
        {
            "etag": "Ndw2BtDw0RinuoqohKBAc8kM-ow",
            "id": {
                "kind": "youtube#video",
                "videoId": "GaewwIBt9Q8"
            },
            "kind": "youtube#searchResult",
            "snippet": {
                "channelId": "UCXoPy1Q1G39fCemCMAmiorQ",
                "channelTitle": "Zico Tops",
                "description": "Descubre como estos juegos saben que mentiste, y encuentran maneras de humillarte y sancionarte por ello, desde Batman, ...",
                "liveBroadcastContent": "none",
                "publishTime": "2023-06-03T01:17:11Z",
                "publishedAt": "2023-06-03T01:17:11Z",
                "thumbnails": {
                    "default": {
                        "height": 90,
                        "url": "https://i.ytimg.com/vi/GaewwIBt9Q8/default.jpg",
                        "width": 120
                    },
                    "high": {
                        "height": 360,
                        "url": "https://i.ytimg.com/vi/GaewwIBt9Q8/hqdefault.jpg",
                        "width": 480
                    },
                    "medium": {
                        "height": 180,
                        "url": "https://i.ytimg.com/vi/GaewwIBt9Q8/mqdefault.jpg",
                        "width": 320
                    }
                },
                "title": "7 Videojuegos que te Castigan por ser un Mentiroso"
            }
        },
        {
            "etag": "MwEMwfsxPvyDo7HLumm87WY5aGU",
            "id": {
                "kind": "youtube#video",
                "videoId": "n2brzilK3kY"
            },
            "kind": "youtube#searchResult",
            "snippet": {
                "channelId": "UCXoPy1Q1G39fCemCMAmiorQ",
                "channelTitle": "Zico Tops",
                "description": "En este Top 7 ver\u00e1s como varias aventuras alegres se pasaron al lado oscuro, de formas incre\u00edbles! Suscribete a Zico Tops para ...",
                "liveBroadcastContent": "none",
                "publishTime": "2022-11-02T22:59:39Z",
                "publishedAt": "2022-11-02T22:59:39Z",
                "thumbnails": {
                    "default": {
                        "height": 90,
                        "url": "https://i.ytimg.com/vi/n2brzilK3kY/default.jpg",
                        "width": 120
                    },
                    "high": {
                        "height": 360,
                        "url": "https://i.ytimg.com/vi/n2brzilK3kY/hqdefault.jpg",
                        "width": 480
                    },
                    "medium": {
                        "height": 180,
                        "url": "https://i.ytimg.com/vi/n2brzilK3kY/mqdefault.jpg",
                        "width": 320
                    }
                },
                "title": "7 Videojuegos Felices que Tuvieron Secuelas muy Oscuras"
            }
        },
        {
            "etag": "Nk2V8v0wP3fGrS8ZsdaAMH1EJ0k",
            "id": {
                "kind": "youtube#video",
                "videoId": "Z7oToktNT_E"
            },
            "kind": "youtube#searchResult",
            "snippet": {
                "channelId": "UCXoPy1Q1G39fCemCMAmiorQ",
                "channelTitle": "Zico Tops",
                "description": "Hay juegos que anticipan la creatividad de los gamers, para ellos lo imposible es una posibilidad, y nos sorprenden a todos.",
                "liveBroadcastContent": "none",
                "publishTime": "2023-04-27T22:54:38Z",
                "publishedAt": "2023-04-27T22:54:38Z",
                "thumbnails": {
                    "default": {
                        "height": 90,
                        "url": "https://i.ytimg.com/vi/Z7oToktNT_E/default.jpg",
                        "width": 120
                    },
                    "high": {
                        "height": 360,
                        "url": "https://i.ytimg.com/vi/Z7oToktNT_E/hqdefault.jpg",
                        "width": 480
                    },
                    "medium": {
                        "height": 180,
                        "url": "https://i.ytimg.com/vi/Z7oToktNT_E/mqdefault.jpg",
                        "width": 320
                    }
                },
                "title": "7 Videojuegos que Sab\u00edan Exactamente lo que Har\u00edas"
            }
        },
        {
            "etag": "lWoIEDzxo583Xzm_fpLPOOO7xvs",
            "id": {
                "kind": "youtube#video",
                "videoId": "Eo4rBMbaNqY"
            },
            "kind": "youtube#searchResult",
            "snippet": {
                "channelId": "UCXoPy1Q1G39fCemCMAmiorQ",
                "channelTitle": "Zico Tops",
                "description": "Descarga la actualizaci\u00f3n de primavera en Warspear Online! https://go.onelink.me/3269616641/bizrjhvd \u00danete a la comunidad ...",
                "liveBroadcastContent": "none",
                "publishTime": "2023-03-30T22:03:14Z",
                "publishedAt": "2023-03-30T22:03:14Z",
                "thumbnails": {
                    "default": {
                        "height": 90,
                        "url": "https://i.ytimg.com/vi/Eo4rBMbaNqY/default.jpg",
                        "width": 120
                    },
                    "high": {
                        "height": 360,
                        "url": "https://i.ytimg.com/vi/Eo4rBMbaNqY/hqdefault.jpg",
                        "width": 480
                    },
                    "medium": {
                        "height": 180,
                        "url": "https://i.ytimg.com/vi/Eo4rBMbaNqY/mqdefault.jpg",
                        "width": 320
                    }
                },
                "title": "7 Videojuegos Populares que Iban a ser Muy Diferentes"
            }
        },
        {
            "etag": "Ivx2AnSeFuoFKcC07JR4Knr5xkY",
            "id": {
                "kind": "youtube#video",
                "videoId": "AMb8EgIaxGc"
            },
            "kind": "youtube#searchResult",
            "snippet": {
                "channelId": "UCq_oSgHK9lk6NUUgkhUOPnw",
                "channelTitle": "DeToxoMoroxo",
                "description": "Descarga MLBB: https://bit.ly/3jI6ZgY Redes Sociales de MLBB: Facebook: ...",
                "liveBroadcastContent": "none",
                "publishTime": "2021-09-04T21:00:56Z",
                "publishedAt": "2021-09-04T21:00:56Z",
                "thumbnails": {
                    "default": {
                        "height": 90,
                        "url": "https://i.ytimg.com/vi/AMb8EgIaxGc/default.jpg",
                        "width": 120
                    },
                    "high": {
                        "height": 360,
                        "url": "https://i.ytimg.com/vi/AMb8EgIaxGc/hqdefault.jpg",
                        "width": 480
                    },
                    "medium": {
                        "height": 180,
                        "url": "https://i.ytimg.com/vi/AMb8EgIaxGc/mqdefault.jpg",
                        "width": 320
                    }
                },
                "title": "7 Videojuegos Con Finales Extra\u00f1os  QUE NADIE Ha Podido Decifrar \ud83e\udd2f | DeToxoMoroxo"
            }
        },
        {
            "etag": "VNkUUkUAUK8G85hhbUQlNKOP10I",
            "id": {
                "kind": "youtube#video",
                "videoId": "OWsNJwRv0mQ"
            },
            "kind": "youtube#searchResult",
            "snippet": {
                "channelId": "UCvmF_tzu-eK6FRfMlOp6-Fg",
                "channelTitle": "Eurogamerspain",
                "description": "Borja, disonancia ludonarrativa y doblajes de Uncharted, qu\u00e9 m\u00e1s se puede pedir. \u00daNETE A EUROGAMER PARA ACCEDER A ...",
                "liveBroadcastContent": "none",
                "publishTime": "2023-03-25T20:33:47Z",
                "publishedAt": "2023-03-25T20:33:47Z",
                "thumbnails": {
                    "default": {
                        "height": 90,
                        "url": "https://i.ytimg.com/vi/OWsNJwRv0mQ/default.jpg",
                        "width": 120
                    },
                    "high": {
                        "height": 360,
                        "url": "https://i.ytimg.com/vi/OWsNJwRv0mQ/hqdefault.jpg",
                        "width": 480
                    },
                    "medium": {
                        "height": 180,
                        "url": "https://i.ytimg.com/vi/OWsNJwRv0mQ/mqdefault.jpg",
                        "width": 320
                    }
                },
                "title": "7 VIDEOJUEGOS en los que el GAMEPLAY contradec\u00eda a LAS CINEM\u00c1TICAS"
            }
        },
        {
            "etag": "mGeX44s09SJCUyr-mplj62xUtaE",
            "id": {
                "kind": "youtube#video",
                "videoId": "JATUYhjqNOI"
            },
            "kind": "youtube#searchResult",
            "snippet": {
                "channelId": "UCHFsrTln0hfwcgZPGctSM6g",
                "channelTitle": "Diki Duki Videojuegos",
                "description": "Hola amiguitos! el d\u00eda de hoy continuamos nuestra aventura en Super Mario Odyssey y esta vez nos encontramos en el Reino ...",
                "liveBroadcastContent": "none",
                "publishTime": "2021-12-17T20:06:18Z",
                "publishedAt": "2021-12-17T20:06:18Z",
                "thumbnails": {
                    "default": {
                        "height": 90,
                        "url": "https://i.ytimg.com/vi/JATUYhjqNOI/default.jpg",
                        "width": 120
                    },
                    "high": {
                        "height": 360,
                        "url": "https://i.ytimg.com/vi/JATUYhjqNOI/hqdefault.jpg",
                        "width": 480
                    },
                    "medium": {
                        "height": 180,
                        "url": "https://i.ytimg.com/vi/JATUYhjqNOI/mqdefault.jpg",
                        "width": 320
                    }
                },
                "title": "ACIDO, ACIDO, ACIDO por TODAS partes | SUPER MARIO ODYSSEY #4"
            }
        },
        {
            "etag": "U9t0nfFtZWQrRJPignu17sdLJM4",
            "id": {
                "kind": "youtube#video",
                "videoId": "2WsRRpieEYo"
            },
            "kind": "youtube#searchResult",
            "snippet": {
                "channelId": "UCDaO4VUeKL0AXXOV7D8knZw",
                "channelTitle": "Un Poco de P\u00edxeles",
                "description": "ADI\u00d3S CONSOLAS?! #shorts #videojuegos #viral #humor En este v\u00eddeo hablamos del futuro de los videojuegos y de lo que ...",
                "liveBroadcastContent": "none",
                "publishTime": "2023-02-08T22:00:00Z",
                "publishedAt": "2023-02-08T22:00:00Z",
                "thumbnails": {
                    "default": {
                        "height": 90,
                        "url": "https://i.ytimg.com/vi/2WsRRpieEYo/default.jpg",
                        "width": 120
                    },
                    "high": {
                        "height": 360,
                        "url": "https://i.ytimg.com/vi/2WsRRpieEYo/hqdefault.jpg",
                        "width": 480
                    },
                    "medium": {
                        "height": 180,
                        "url": "https://i.ytimg.com/vi/2WsRRpieEYo/mqdefault.jpg",
                        "width": 320
                    }
                },
                "title": "ADI\u00d3S CONSOLAS?! \ud83e\udd15 #shorts"
            }
        }
    ],
    "kind": "youtube#searchListResponse",
    "nextPageToken": "CDIQAA",
    "pageInfo": {
        "resultsPerPage": 50,
        "totalResults": 1000000
    },
    "regionCode": "ES"
}